poetry_plugin_pyenv/__init__.py
poetry_plugin_pyenv/plugin.py
poetry_plugin_pyenv/py.typed
poetry_plugin_pyenv/pyenv.py
poetry_plugin_pyenv-0.2.1.dist-info/LICENSE
poetry_plugin_pyenv-0.2.1.dist-info/METADATA
poetry_plugin_pyenv-0.2.1.dist-info/WHEEL
poetry_plugin_pyenv-0.2.1.dist-info/entry_points.txt
poetry_plugin_pyenv-0.2.1.dist-info/RECORD
