Metadata-Version: 2.1
Name: poetry-plugin-pyenv
Version: 0.2.1
Summary: 
Home-page: https://github.com/tjquillan/poetry-plugin-pyenv
License: MIT
Keywords: poetry,plugin,pyenv
Author: tjquillan
Author-email: tjquillan@gmail.com
Requires-Python: >=3.8,<4.0
Classifier: Development Status :: 3 - Alpha
Classifier: Environment :: Plugins
Classifier: Intended Audience :: Developers
Classifier: License :: OSI Approved :: MIT License
Classifier: Natural Language :: English
Classifier: Operating System :: OS Independent
Classifier: Programming Language :: Python :: 3
Classifier: Programming Language :: Python :: 3.8
Classifier: Programming Language :: Python :: 3.9
Classifier: Programming Language :: Python :: 3.10
Classifier: Programming Language :: Python :: 3.11
Classifier: Programming Language :: Python :: 3.12
Classifier: Topic :: Software Development
Classifier: Topic :: Software Development :: Libraries
Classifier: Typing :: Typed
Requires-Dist: poetry (>=1.3,<2.0)
Project-URL: Repository, https://github.com/tjquillan/poetry-plugin-pyenv
